cns/DataX.cp310-win_amd64.pyd
cns/DateTimeX.cp310-win_amd64.pyd
cns/ExcelX.cp310-win_amd64.pyd
cns/OTPX.cp310-win_amd64.pyd
cns/ProX.py
cns/TextX.cp310-win_amd64.pyd
cns/__init__.py
cns/cmdX.cp310-win_amd64.pyd
cns/crt_mgr.cp310-win_amd64.pyd
cns/sqlX.cp310-win_amd64.pyd
cns/ssl.cp310-win_amd64.pyd
cns/strX.cp310-win_amd64.pyd
cns-2.3.50.dist-info/LICENSE
cns-2.3.50.dist-info/METADATA
cns-2.3.50.dist-info/WHEEL
cns-2.3.50.dist-info/top_level.txt
cns-2.3.50.dist-info/RECORD
