Metadata-Version: 2.1
Name: cns
Version: 2.3.50
Summary: cns工具包
Author-email: Rambo <6566666@qq.com>
Maintainer-email: Rmbo <6566666@qq.com>
License: MIT License
Project-URL: home, https://cns.ink/example
Keywords: cns,工具包,特定功能关键词
Classifier: Development Status :: 3 - Alpha
Classifier: Programming Language :: Python :: 3
Classifier: Operating System :: Microsoft :: Windows
Classifier: Topic :: Utilities
Requires-Python: >=3.10
License-File: LICENSE
Requires-Dist: python-dateutil>=2.9.0
Requires-Dist: cryptography>=44.0.2
